{
  "schema_version": 1,
  "business_stage": "local_evidence_mvp_verified_external_launch_blocked",
  "selected_business": "CapabilityProof (internal codename; public name TBD)",
  "selected_offer": "Registry-neutral, independent, exact-byte policy receipt for one Agent Skill version",
  "current_goal": "Reach every charter acceptance test without overstating the verified local MVP or commercial demand",
  "acceptance_tests": {
    "specific_segment_and_problem": "documented_problem_supported_segment_demand_unvalidated",
    "opportunity_supported_by_current_evidence": "problem_supported_commercial_demand_unproven",
    "complete_offer": "draft_revised_not_live",
    "live_acquisition_path": "pending_launch_readiness",
    "working_sales_and_payment_path": "pending_owner_approval_and_launch_readiness",
    "three_unaffiliated_paying_customers": "pending",
    "settled_gross_revenue_500": "pending",
    "successful_delivery": "pending_no_customer_delivery",
    "delivery_quality_checks": "local_mvp_34_passed_1_platform_skip_independent_review_pass",
    "revenue_is_external_and_genuine": "pending",
    "positive_contribution_margin": "pending",
    "owner_spending_within_100": "passing_zero_spend",
    "complete_material_records": "passing_for_current_stage",
    "repeatable_acquisition_process": "pending",
    "repeatable_fulfillment_process": "local_prototype_verified_not_customer_validated",
    "independent_audit_pass": "local_mvp_scope_pass_external_and_goal_audits_pending"
  },
  "cash_budget_remaining_usd": 100.0,
  "owner_funded_spending_usd": 0.0,
  "collected_revenue_usd": 0.0,
  "pending_revenue_usd": 0.0,
  "refund_exposure_usd": 0.0,
  "current_customers": [],
  "pipeline_metrics": {
    "qualified_prospects": 0,
    "contacted": 0,
    "responses": 0,
    "proposals": 0,
    "wins": 0
  },
  "completed_experiments": [
    "E-001 real public Agent Skill receipt generation and independent local-MVP review"
  ],
  "active_experiments": [],
  "planned_experiments": [
    "E-002 full-price portable receipt and policy-pack transaction test after launch readiness"
  ],
  "current_blockers": [
    "CapabilityProof is conflicted as a public name",
    "No immutable external upload or isolated no-egress worker",
    "No external authentication, TLS, authorization, or tenant isolation",
    "No RFC 8785 JCS signature, authenticated key, rotation, revocation, or invalidation",
    "No approved payment/KYC path"
  ],
  "human_actions_requested": [],
  "top_next_actions": [
    "Select and screen a distinctive public name before publishing a package, domain, badge, or namespace",
    "Specify and regression-test raw ZIP intake plus an isolated no-egress worker profile",
    "Build a truthful static demand-test page locally without accepting artifacts or payment"
  ],
  "last_verified_external_state": "No external CapabilityProof asset has been published, no customer contacted, no payment path opened, and no money spent.",
  "last_checkpoint_time": "2026-07-13T21:16:51-07:00",
  "exact_resume_instruction": "Read CHARTER.md, GOAL.md, STATE.json, STATUS.md, BACKLOG.md, NEXT_ACTION.md, BUDGET.csv, REVENUE.csv, EXPERIMENTS.csv, CRM.csv, HUMAN_ACTIONS.md, logs/2026-07-13-e001-verification.md, and research/independent-mvp-review.md. Preserve the local-only boundary; continue the public-name and external-safe intake gate without publishing, accepting artifacts, opening payment accounts, or spending unless separately authorized."
}
